setup.cfg
setup.py
dbf2csv/__init__.py
dbf2csv/main.py
dbf2csv.egg-info/PKG-INFO
dbf2csv.egg-info/SOURCES.txt
dbf2csv.egg-info/dependency_links.txt
dbf2csv.egg-info/entry_points.txt
dbf2csv.egg-info/requires.txt
dbf2csv.egg-info/top_level.txt