Metadata-Version: 1.0
Name: dbf2csv
Version: 1.3
Summary: Small utility to convert simple *.DBF files to *.CSV
Home-page: https://github.com/akadan47/dbf2csv
Author: UNKNOWN
Author-email: UNKNOWN
License: UNKNOWN
Platform: any
